AmosMsg/AmosMsg.py
AmosMsg/__init__.py
AmosMsg-0.0.3.dist-info/METADATA
AmosMsg-0.0.3.dist-info/WHEEL
AmosMsg-0.0.3.dist-info/top_level.txt
AmosMsg-0.0.3.dist-info/RECORD
