Metadata-Version: 2.1
Name: AmosMsg
Version: 0.0.3
Summary: MQ Consumer
Home-page: https://github.com/bowofamos/amos#readme
Author: ganyu
Author-email: amosbow@163.com
Requires-Dist: PyYAML
Requires-Dist: pika
